{
  "tests": [
    {
      "name": "Verify implementation of prob01",
      "setup": "true",
      "run": "cd prob01 && make build",
      "input": "",
      "output": "",
      "comparison": "included",
      "timeout": 3,
      "points": 1
    },
    {
      "name": "Verify implementation of prob02",
      "setup": "",
      "run": "cd prob02 && make build",
      "input": "",
      "output": "",
      "comparison": "included",
      "timeout": 3,
      "points": 1
    },
    {
      "name": "Verify implementation of prob03",
      "setup": "",
      "run": "cd prob03 && make build",
      "input": "",
      "output": "",
      "comparison": "included",
      "timeout": 3,
      "points": 1
    },
    {
      "name": "Check readability of prob01",
      "setup": "",
      "run": "cd prob01 && make clean && make stylecheck && make formatcheck",
      "input": "",
      "output": "",
      "comparison": "included",
      "timeout": 3,
      "points": 1
    },
    {
      "name": "Check readability of prob02",
      "setup": "",
      "run": "cd prob02 && make clean && make stylecheck && make formatcheck",
      "input": "",
      "output": "",
      "comparison": "included",
      "timeout": 3,
      "points": 1
    },
    {
      "name": "Check readability of prob03",
      "setup": "",
      "run": "cd prob03 && make clean && make stylecheck && make formatcheck",
      "input": "",
      "output": "",
      "comparison": "included",
      "timeout": 3,
      "points": 1
    },
    {
      "name": "Prob01 All tests",
      "setup": "",
      "run": "cd prob01 && make clean && make test",
      "input": "",
      "output": "",
      "comparison": "included",
      "timeout": 3,
      "points": 6
    },
    {
      "name": "Prob02 all tests",
      "setup": "",
      "run": "cd prob02 && make clean && make test",
      "input": "",
      "output": "",
      "comparison": "included",
      "timeout": 3,
      "points": 7
    },
    {
      "name": "Prob03 all tests",
      "setup": "",
      "run": "cd prob03 && make clean && make test",
      "input": "",
      "output": "",
      "comparison": "included",
      "timeout": 3,
      "points": 6
    },
    {
      "name": "Prob01 return 0 when the vector has one element",
      "setup": "",
      "run": "cd prob01 && make clean && make build && ./main",
      "input": "1\r\n42",
      "output": "0",
      "comparison": "included",
      "timeout": 3,
      "points": 1
    }
  ]
}